search-suggestion.py
search/__init__.py
search_suggestion/__init__.py
search_suggestion/search-suggestion.py
search_suggestion/search_suggestion.py
search_suggestion-0.1.0.dist-info/LICENSE
search_suggestion-0.1.0.dist-info/METADATA
search_suggestion-0.1.0.dist-info/WHEEL
search_suggestion-0.1.0.dist-info/top_level.txt
search_suggestion-0.1.0.dist-info/RECORD
