Metadata-Version: 2.1
Name: search-suggestion
Version: 0.1.0
Summary: Search query suggestion service
Home-page: https://github.com/5tigerjelly/search-suggestion-python
Author: Chris Oh
Author-email: chris@5tigerjelly.com
License: UNKNOWN
Keywords: search,autosuggestion,suggestion
Platform: UNKNOWN
Classifier: Development Status :: 4 - Beta
Classifier: Programming Language :: Python :: 3
Classifier: Programming Language :: Python :: 3.6
Classifier: Programming Language :: Python :: 3.7
Classifier: Programming Language :: Python :: 3.8
Classifier: Programming Language :: Python :: 3.9
Classifier: Programming Language :: Python :: 3 :: Only
Classifier: License :: OSI Approved :: MIT License
Classifier: Operating System :: OS Independent
Requires-Python: >=3.6
